{
    "Africa": 2125,
    "Americas": 25694,
    "Asia": 6034,
    "Australia and New Zealand": 62371,
    "Caribbean": 7751,
    "Central America": 8806,
    "Central Asia": 5263,
    "China, Hong Kong SAR": 38567,
    "China, Macao Special Administrative Region": 89525,
    "Curaçao": 20321,
    "Eastern Africa": 783,
    "Eastern Asia": 10471,
    "Eastern Europe": 12636,
    "Europe": 29462,
    "Latin America and the Caribbean": 10267,
    "Melanesia": 3899,
    "Micronesia": 3435,
    "Micronesia (Federated States of)": 3048,
    "Middle Africa": 1872,
    "Northern Africa": 3523,
    "Northern America": 52840,
    "Northern Europe": 47284,
    "Oceania": 46481,
    "Polynesia": 12728,
    "Republic of Korea": 26024,
    "Republic of Moldova": 1961,
    "South America": 11125,
    "South-Eastern Asia": 4058,
    "Southern Africa": 6515,
    "Southern Asia": 1660,
    "Southern Europe": 27268,
    "State of Palestine": 2826,
    "Sub-Saharan Africa": 1796,
    "The former Yugoslav Republic of Macedonia": 5211,
    "United Kingdom of Great Britain and Northern Ireland": 42385,
    "United Republic of Tanzania: Zanzibar": 835,
    "Western Africa": 2035,
    "Western Asia": 13530,
    "Western Europe": 47446,
    "World": 10683
}