{
    "Africa": 631899,
    "Americas": 13624376,
    "Asia": 8852402,
    "Australia and New Zealand": 444205,
    "Caribbean": 171784,
    "Central America": 830798,
    "Central Asia": 40850,
    "China, Hong Kong SAR": 169404,
    "China, Macao Special Administrative Region": 6811,
    "Eastern Africa": 79279,
    "Eastern Asia": 6669800,
    "Eastern Europe": 748100,
    "Europe": 9848149,
    "Former Netherlands Antilles": 2899,
    "Former Sudan": 15716,
    "Latin America and the Caribbean": 2261401,
    "Melanesia": 10177,
    "Micronesia": 598,
    "Micronesia (Federated States of)": 240,
    "Middle Africa": 43895,
    "Northern Africa": 257264,
    "Northern America": 11362975,
    "Northern Europe": 2473692,
    "Oceania": 459188,
    "Polynesia": 4208,
    "Republic of Korea": 533050,
    "Republic of Moldova": 1481,
    "South America": 1258820,
    "South-Eastern Asia": 602034,
    "Southern Africa": 134748,
    "Southern Asia": 737759,
    "Southern Europe": 2126482,
    "State of Palestine": 4004,
    "Sub-Saharan Africa": 374635,
    "The former Yugoslav Republic of Macedonia": 3710,
    "United Kingdom of Great Britain and Northern Ireland": 1621615,
    "United Republic of Tanzania: Zanzibar": 317,
    "Western Africa": 116713,
    "Western Asia": 801960,
    "Western Europe": 4499876,
    "World": 33416015
}